uniovi_simur_wearablepermed_ml-1.9.0.dist-info/licenses/LICENSE.txt
wearablepermed_ml/__init__.py
wearablepermed_ml/boxplots.py
wearablepermed_ml/run_trainer_and_tester_30_times.py
wearablepermed_ml/tester.py
wearablepermed_ml/trainer.py
wearablepermed_ml/basic_functions/__init__.py
wearablepermed_ml/basic_functions/address.py
wearablepermed_ml/data/DataReader.py
wearablepermed_ml/data/__init__.py
wearablepermed_ml/models/SiMuR_Model.py
wearablepermed_ml/models/__init__.py
wearablepermed_ml/models/model_generator.py
wearablepermed_ml/testing/__init__.py
wearablepermed_ml/testing/testing.py
uniovi_simur_wearablepermed_ml-1.9.0.dist-info/METADATA
uniovi_simur_wearablepermed_ml-1.9.0.dist-info/WHEEL
uniovi_simur_wearablepermed_ml-1.9.0.dist-info/entry_points.txt
uniovi_simur_wearablepermed_ml-1.9.0.dist-info/top_level.txt
uniovi_simur_wearablepermed_ml-1.9.0.dist-info/RECORD
