Metadata-Version: 2.4
Name: uniovi-simur-wearablepermed-ml
Version: 1.9.0
Summary: Uniovi Simur WearablePerMed Machine Learning.
Home-page: https://github.com/Simur-project/uniovi-simur-wearablepermed-ml.git
Author: Miguel Salinas Gancedo
Author-email: masalinas.gancedo@gmail.com
License: MIT
Project-URL: Documentation, https://pyscaffold.org/
Platform: any
Classifier: Development Status :: 4 - Beta
Classifier: Programming Language :: Python
License-File: LICENSE.txt
Requires-Dist: importlib-metadata; python_version < "3.8"
Requires-Dist: absl-py==2.3.0
Requires-Dist: alabaster==1.0.0
Requires-Dist: astunparse==1.6.3
Requires-Dist: attrs==25.3.0
Requires-Dist: babel==2.17.0
Requires-Dist: cachetools==6.0.0
Requires-Dist: certifi==2025.4.26
Requires-Dist: chardet==5.2.0
Requires-Dist: charset-normalizer==3.4.2
Requires-Dist: click==8.2.1
Requires-Dist: colorama==0.4.6
Requires-Dist: ConfigUpdater==3.2
Requires-Dist: contourpy==1.3.2
Requires-Dist: cycler==0.12.1
Requires-Dist: distlib==0.3.9
Requires-Dist: docutils==0.21.2
Requires-Dist: et_xmlfile==2.0.0
Requires-Dist: filelock==3.18.0
Requires-Dist: flatbuffers==25.2.10
Requires-Dist: fonttools==4.58.2
Requires-Dist: fsspec==2025.7.0
Requires-Dist: gast==0.6.0
Requires-Dist: google-pasta==0.2.0
Requires-Dist: grpcio==1.73.0
Requires-Dist: h5py==3.14.0
Requires-Dist: idna==3.10
Requires-Dist: imagesize==1.4.1
Requires-Dist: imbalanced-learn==0.13.0
Requires-Dist: imblearn==0.0
Requires-Dist: importlib_metadata==8.7.0
Requires-Dist: importlib_resources==6.5.2
Requires-Dist: Jinja2==3.1.6
Requires-Dist: joblib==1.5.1
Requires-Dist: jsonschema==4.25.0
Requires-Dist: jsonschema-specifications==2025.4.1
Requires-Dist: keras==3.10.0
Requires-Dist: keras-tuner==1.4.7
Requires-Dist: kiwisolver==1.4.8
Requires-Dist: kt-legacy==1.0.5
Requires-Dist: libclang==18.1.1
Requires-Dist: linkify-it-py==2.0.3
Requires-Dist: lxml==5.4.0
Requires-Dist: Markdown==3.8
Requires-Dist: markdown-it-py==3.0.0
Requires-Dist: MarkupSafe==3.0.2
Requires-Dist: matplotlib==3.10.3
Requires-Dist: mdit-py-plugins==0.4.2
Requires-Dist: mdurl==0.1.2
Requires-Dist: ml_dtypes==0.5.1
Requires-Dist: msgpack==1.1.1
Requires-Dist: myst-parser==4.0.1
Requires-Dist: namex==0.1.0
Requires-Dist: numpy==1.26.4
Requires-Dist: openpyxl==3.1.5
Requires-Dist: opt_einsum==3.4.0
Requires-Dist: optree==0.16.0
Requires-Dist: packaging==25.0
Requires-Dist: pandas==2.3.0
Requires-Dist: pandas-datareader==0.10.0
Requires-Dist: patsy==1.0.1
Requires-Dist: pillow==11.2.1
Requires-Dist: platformdirs==4.3.8
Requires-Dist: pluggy==1.6.0
Requires-Dist: protobuf==5.29.5
Requires-Dist: pur==7.3.3
Requires-Dist: pyarrow==21.0.0
Requires-Dist: Pygments==2.19.1
Requires-Dist: pyparsing==3.2.3
Requires-Dist: pyproject-api==1.9.1
Requires-Dist: PyScaffold==4.6
Requires-Dist: pyscaffoldext-markdown==0.5
Requires-Dist: python-dateutil==2.9.0.post0
Requires-Dist: pytz==2025.2
Requires-Dist: PyYAML==6.0.2
Requires-Dist: ray==2.48.0
Requires-Dist: referencing==0.36.2
Requires-Dist: requests==2.32.4
Requires-Dist: rich==14.0.0
Requires-Dist: roman-numerals-py==3.1.0
Requires-Dist: rpds-py==0.26.0
Requires-Dist: scikit-learn==1.6.1
Requires-Dist: scipy==1.16.2
Requires-Dist: seaborn==0.13.2
Requires-Dist: setuptools==80.9.0
Requires-Dist: setuptools-scm==8.3.1
Requires-Dist: six==1.17.0
Requires-Dist: sklearn-compat==0.1.3
Requires-Dist: snowballstemmer==3.0.1
Requires-Dist: Sphinx==8.2.3
Requires-Dist: sphinxcontrib-applehelp==2.0.0
Requires-Dist: sphinxcontrib-devhelp==2.0.0
Requires-Dist: sphinxcontrib-htmlhelp==2.1.0
Requires-Dist: sphinxcontrib-jsmath==1.0.1
Requires-Dist: sphinxcontrib-qthelp==2.0.0
Requires-Dist: sphinxcontrib-serializinghtml==2.0.0
Requires-Dist: statsmodels==0.14.4
Requires-Dist: tensorboard==2.19.0
Requires-Dist: tensorboard-data-server==0.7.2
Requires-Dist: tensorboardX==2.6.4
Requires-Dist: tensorflow==2.19.0
Requires-Dist: termcolor==3.1.0
Requires-Dist: tf_keras==2.19.0
Requires-Dist: threadpoolctl==3.6.0
Requires-Dist: tomli==2.2.1
Requires-Dist: tomlkit==0.13.3
Requires-Dist: tox==4.26.0
Requires-Dist: typing_extensions==4.14.0
Requires-Dist: tzdata==2025.2
Requires-Dist: uc-micro-py==1.0.3
Requires-Dist: urllib3==2.4.0
Requires-Dist: virtualenv==20.31.2
Requires-Dist: Werkzeug==3.1.3
Requires-Dist: wheel==0.45.1
Requires-Dist: wrapt==1.17.2
Requires-Dist: xgboost==2.0.3
Requires-Dist: zipp==3.23.0
Provides-Extra: testing
Requires-Dist: setuptools; extra == "testing"
Requires-Dist: pytest; extra == "testing"
Requires-Dist: pytest-cov; extra == "testing"
Dynamic: license-file
